{
	"info": {
		"_postman_id": "23a52d16-b8ae-45eb-845c-0971a318b56c",
		"name": "ARC-Project",
		"schema": "https://schema.getpostman.com/json/collection/v2.1.0/collection.json"
	},
	"item": [
		{
			"name": "Words",
			"item": [
				{
					"name": "Single word",
					"request": {
						"method": "GET",
						"header": [],
						"url": {
							"raw": "http://localhost:3000/word/SKTWeqwuTxTImjmYTzp3",
							"protocol": "http",
							"host": [
								"localhost"
							],
							"port": "3000",
							"path": [
								"word",
								"SKTWeqwuTxTImjmYTzp3"
							]
						}
					},
					"response": []
				},
				{
					"name": "Multiple words",
					"request": {
						"method": "GET",
						"header": [],
						"url": {
							"raw": "http://localhost:3000/word/",
							"protocol": "http",
							"host": [
								"localhost"
							],
							"port": "3000",
							"path": [
								"word",
								""
							]
						}
					},
					"response": []
				},
				{
					"name": "Add a word",
					"request": {
						"method": "POST",
						"header": [],
						"url": {
							"raw": "http://localhost:3000/word/add/Ogórek/El Pepino",
							"protocol": "http",
							"host": [
								"localhost"
							],
							"port": "3000",
							"path": [
								"word",
								"add",
								"Ogórek",
								"El Pepino"
							]
						}
					},
					"response": []
				},
				{
					"name": "Add a word new",
					"request": {
						"method": "POST",
						"header": [],
						"body": {
							"mode": "formdata",
							"formdata": [
								{
									"key": "local",
									"value": "Test",
									"type": "text"
								},
								{
									"key": "foreign",
									"value": "Testerino",
									"type": "text"
								}
							]
						},
						"url": {
							"raw": "http://localhost:3000/word/add/",
							"protocol": "http",
							"host": [
								"localhost"
							],
							"port": "3000",
							"path": [
								"word",
								"add",
								""
							]
						}
					},
					"response": []
				},
				{
					"name": "Delete a word",
					"request": {
						"method": "DELETE",
						"header": [],
						"url": {
							"raw": "http://localhost:3000/word/del/GWebjGYkR3mzNCW7JpCj",
							"protocol": "http",
							"host": [
								"localhost"
							],
							"port": "3000",
							"path": [
								"word",
								"del",
								"GWebjGYkR3mzNCW7JpCj"
							]
						}
					},
					"response": []
				}
			]
		},
		{
			"name": "Login",
			"item": [
				{
					"name": "Register",
					"request": {
						"method": "POST",
						"header": [],
						"body": {
							"mode": "formdata",
							"formdata": [
								{
									"key": "email",
									"value": "test@gmail.com",
									"type": "text"
								},
								{
									"key": "password",
									"value": "test1234",
									"type": "text"
								}
							]
						},
						"url": {
							"raw": "http://localhost:3000/account/register",
							"protocol": "http",
							"host": [
								"localhost"
							],
							"port": "3000",
							"path": [
								"account",
								"register"
							]
						}
					},
					"response": []
				}
			]
		}
	]
}